dcrtrs-0.1.0.dist-info/dependency_links.txt
dcrtrs-0.1.0.dist-info/entry_points.txt
dcrtrs-0.1.0.dist-info/METADATA
dcrtrs-0.1.0.dist-info/top_level.txt
dcrtrs-0.1.0.dist-info/WHEEL
_timer.py
_single_dispatch_method.py
_cached_property.py
_method_decorator.py
__init__.py
_class_only_method.py
_class_property.py
_debug.py
dcrtrs-0.1.0.dist-info/RECORD