Metadata-Version: 2.1
Name: dcrtrs
Version: 0.1.0
Summary: Collection of useful decorators
Author: Gram (@orsinium)